pynxhuy/__init__.py
pynxhuy/modules.py
pynxhuy-0.3.dist-info/LICENSE
pynxhuy-0.3.dist-info/METADATA
pynxhuy-0.3.dist-info/WHEEL
pynxhuy-0.3.dist-info/top_level.txt
pynxhuy-0.3.dist-info/RECORD
