Metadata-Version: 2.1
Name: pynxhuy
Version: 0.3
Summary: The nxhuyiest joke in the world
Home-page: https://github.com/nxhuy-github/pynxhuy
Author: Xuan Huy NGUYEN
Author-email: nxhuy@example.com
License: UNKNOWN
Platform: UNKNOWN
